odoo8_addon_l10n_ar_point_of_sale-8.0.1.1.0.99.dev10-py2.7-nspkg.pth
odoo8_addon_l10n_ar_point_of_sale-8.0.1.1.0.99.dev10.dist-info/METADATA
odoo8_addon_l10n_ar_point_of_sale-8.0.1.1.0.99.dev10.dist-info/RECORD
odoo8_addon_l10n_ar_point_of_sale-8.0.1.1.0.99.dev10.dist-info/WHEEL
odoo8_addon_l10n_ar_point_of_sale-8.0.1.1.0.99.dev10.dist-info/namespace_packages.txt
odoo8_addon_l10n_ar_point_of_sale-8.0.1.1.0.99.dev10.dist-info/top_level.txt
odoo_addons/l10n_ar_point_of_sale/.gitignore
odoo_addons/l10n_ar_point_of_sale/.travis.yml
odoo_addons/l10n_ar_point_of_sale/AUTHORS
odoo_addons/l10n_ar_point_of_sale/__init__.py
odoo_addons/l10n_ar_point_of_sale/__openerp__.py
odoo_addons/l10n_ar_point_of_sale/account.py
odoo_addons/l10n_ar_point_of_sale/account_invoice_view.xml
odoo_addons/l10n_ar_point_of_sale/account_view.xml
odoo_addons/l10n_ar_point_of_sale/invoice.py
odoo_addons/l10n_ar_point_of_sale/partner.py
odoo_addons/l10n_ar_point_of_sale/partner_data.xml
odoo_addons/l10n_ar_point_of_sale/partner_demo.xml
odoo_addons/l10n_ar_point_of_sale/partner_view.xml
odoo_addons/l10n_ar_point_of_sale/pos_ar.py
odoo_addons/l10n_ar_point_of_sale/pos_ar_view.xml
odoo_addons/l10n_ar_point_of_sale/purchase.py
odoo_addons/l10n_ar_point_of_sale/sale.py
odoo_addons/l10n_ar_point_of_sale/sale_view.xml
odoo_addons/l10n_ar_point_of_sale/stock.py
odoo_addons/l10n_ar_point_of_sale/i18n/es_AR.po
odoo_addons/l10n_ar_point_of_sale/security/ir.model.access.csv
odoo_addons/l10n_ar_point_of_sale/static/description/icon.png
odoo_addons/l10n_ar_point_of_sale/test/denomination_invoice.yml
odoo_addons/l10n_ar_point_of_sale/travis_scripts/create_db.py
odoo_addons/l10n_ar_point_of_sale/travis_scripts/createdb.sh
odoo_addons/l10n_ar_point_of_sale/travis_scripts/requirements.txt
odoo_addons/l10n_ar_point_of_sale/wizard/__init__.py
odoo_addons/l10n_ar_point_of_sale/wizard/purchase_line_invoice.py
odoo_addons/l10n_ar_point_of_sale/wizard/sale_line_invoice.py
