Metadata-Version: 2.1
Name: odoo8-addon-l10n-ar-point-of-sale
Version: 8.0.1.1.0.99.dev10
Summary: Point of Sale ARGENTINA
Home-page: http://proyectoaconcagua.com.ar
Author: E-MIPS/Proyecto Aconcagua,Odoo Community Association (OCA)
Author-email: support@odoo-community.org
License: GPL-3
Platform: UNKNOWN
Classifier: Programming Language :: Python
Classifier: Framework :: Odoo
Classifier: License :: OSI Approved :: GNU General Public License v3 (GPLv3)
Requires-Python: ~=2.7
Requires-Dist: odoo8-addon-base-vat-ar
Requires-Dist: odoo (<9.0a,>=8.0a)
